{
  "id": "1744946932967",
  "name": "1",
  "createdAt": "2025-04-18T03:28:52.967Z",
  "updatedAt": "2025-04-18T03:49:48.826Z",
  "description": "",
  "content": {
    "main_setting_of_the_worldview": {
      "updatedAt": "2025-04-18T03:49:48.826Z",
      "content": {
        "text": "# 世界观名称\n\n## 背景设定\n\n在这里描述世界的基本背景和设定...\n\n## 主要时间线\n\n### 远古时代\n\n远古时代的重要事件...\n\n### 中世纪\n\n中世纪的重要事件...\n\n## 世界规则\n\n### 魔法系统\n\n这个世界的魔法是如何运作的...\n\n### 科技水平\n\n这个世界的科技发展到了什么程度...\n\n## 重要地点\n\n## 重要人物\n\n13413412341234123424113241234123412341234\n"
      }
    }
  }
}